reservoir_computing/__init__.py
reservoir_computing/datasets.py
reservoir_computing/modules.py
reservoir_computing/reservoir.py
reservoir_computing/tensorPCA.py
reservoir_computing/utils.py
reservoir_computing-1.0.2.dist-info/LICENSE
reservoir_computing-1.0.2.dist-info/METADATA
reservoir_computing-1.0.2.dist-info/WHEEL
reservoir_computing-1.0.2.dist-info/top_level.txt
reservoir_computing-1.0.2.dist-info/RECORD
