Metadata-Version: 2.2
Name: reservoir_computing
Version: 1.0.2
Summary: Library for implementing reservoir computing models (Echo State Networks) for multivariate time series classification, clustering, and forecasting.
Author: Filippo Maria Bianchi
Author-email: filippombianchi@gmail.com
Project-URL: Documentation, https://reservoir-computing.readthedocs.io/en/latest/
Project-URL: Source Code, https://github.com/FilippoMB/Time-series-classification-and-clustering-with-Reservoir-Computing
Classifier: Programming Language :: Python :: 3
Classifier: License :: OSI Approved :: MIT License
Classifier: Operating System :: OS Independent
Requires-Python: >=3.9
License-File: LICENSE
Requires-Dist: numpy>1.19.5
Requires-Dist: scikit_learn>=1.4
Requires-Dist: scipy
Requires-Dist: requests
Requires-Dist: matplotlib
Dynamic: author
Dynamic: author-email
Dynamic: classifier
Dynamic: description
Dynamic: description-content-type
Dynamic: project-url
Dynamic: requires-dist
Dynamic: requires-python
Dynamic: summary
